blackboard_sync/__about__.py
blackboard_sync/__init__.py
blackboard_sync/__main__.py
blackboard_sync/config.py
blackboard_sync/download.py
blackboard_sync/executor.py
blackboard_sync/institutions.py
blackboard_sync/ip.py
blackboard_sync/sync.py
blackboard_sync/sync_controller.py
blackboard_sync/universities.json
blackboard_sync/updates.py
blackboard_sync/assets/WizardPixmap.BackgroundPixmap.png
blackboard_sync/assets/logo.png
blackboard_sync/content/__init__.py
blackboard_sync/content/api_path.py
blackboard_sync/content/attachment.py
blackboard_sync/content/base.py
blackboard_sync/content/body.py
blackboard_sync/content/content.py
blackboard_sync/content/course.py
blackboard_sync/content/document.py
blackboard_sync/content/externallink.py
blackboard_sync/content/folder.py
blackboard_sync/content/job.py
blackboard_sync/content/templates.py
blackboard_sync/content/unhandled.py
blackboard_sync/content/webdav.py
blackboard_sync/qt/LoginWebView.py
blackboard_sync/qt/LoginWebView.ui
blackboard_sync/qt/SettingsWindow.py
blackboard_sync/qt/SettingsWindow.ui
blackboard_sync/qt/SetupWizard.py
blackboard_sync/qt/SetupWizard.ui
blackboard_sync/qt/SyncTrayIcon.py
blackboard_sync/qt/__init__.py
blackboard_sync/qt/assets.py
blackboard_sync/qt/dialogs.py
blackboard_sync/qt/manager.py
blackboard_sync/qt/notification.py
blackboard_sync/qt/utils.py
blackboard_sync/qt/translations/de.qm
blackboard_sync/qt/translations/de.ts
blackboard_sync/qt/translations/es.qm
blackboard_sync/qt/translations/es.ts
blackboard_sync/qt/translations/fr.qm
blackboard_sync/qt/translations/fr.ts
blackboardsync-0.18.0.dist-info/LICENSE
blackboardsync-0.18.0.dist-info/METADATA
blackboardsync-0.18.0.dist-info/WHEEL
blackboardsync-0.18.0.dist-info/entry_points.txt
blackboardsync-0.18.0.dist-info/top_level.txt
blackboardsync-0.18.0.dist-info/RECORD
