Metadata-Version: 2.1
Name: blackboardsync
Version: 0.18.0
Summary: Sync your blackboard content to your device
Author-email: Jacob Sánchez <jacobszpz@protonmail.com>
Project-URL: Homepage, https://bbsync.app
Project-URL: Repository, https://github.com/sanjacob/BlackboardSync
Project-URL: Bug Tracker, https://github.com/sanjacob/BlackboardSync/issues
Classifier: Programming Language :: Python :: 3.10
Classifier: License :: OSI Approved :: GNU General Public License v2 (GPLv2)
Classifier: Operating System :: OS Independent
Classifier: Intended Audience :: Education
Classifier: Intended Audience :: End Users/Desktop
Classifier: Topic :: Education
Requires-Python: >=3.10
License-File: LICENSE
Requires-Dist: pyqt6 >=6.7.1
Requires-Dist: pyqt6-webengine >=6.7.0
Requires-Dist: beautifulsoup4 >=4.12.2
Requires-Dist: pydantic >=2.1.1
Requires-Dist: pathvalidate >=3.1.0
Requires-Dist: python-dateutil ==2.9.0.post0
Requires-Dist: appdirs ==1.4.4
Requires-Dist: lxml >=4.7.1
Requires-Dist: requests >=2.25.0
Requires-Dist: packaging >=23.1
Requires-Dist: bblearn >=0.3.0
Requires-Dist: whoisit
Requires-Dist: bwfilters
Provides-Extra: package
Requires-Dist: pyinstaller >=5.13.2 ; extra == 'package'
Requires-Dist: build ; extra == 'package'
Requires-Dist: twine ; extra == 'package'
Provides-Extra: test
Requires-Dist: pytest ; extra == 'test'
Requires-Dist: hypothesis ; extra == 'test'
Requires-Dist: coverage ; extra == 'test'
Requires-Dist: pytest-qt ; extra == 'test'
Requires-Dist: pytest-mock ; extra == 'test'
